geosampler/__init__.py
geosampler/sampler.py
geosampler/utils.py
geosampler-0.1.3.dist-info/WHEEL
geosampler-0.1.3.dist-info/METADATA
geosampler-0.1.3.dist-info/RECORD
