Metadata-Version: 2.1
Name: geosampler
Version: 0.1.3
Summary: A simple way to collect samples for social sciences experiments
Author: Gloria Macia
Author-email: gloria.macia@roche.com
Requires-Python: >=3.8,<4
Classifier: Programming Language :: Python :: 3
Classifier: Programming Language :: Python :: 3.10
Classifier: Programming Language :: Python :: 3.8
Classifier: Programming Language :: Python :: 3.9
Requires-Dist: folium (>=0.12.1,<0.13.0)
Requires-Dist: pandas (>=1.5.0,<2.0.0)
Requires-Dist: requests (>=2.28.1,<3.0.0)
Requires-Dist: tqdm (>=4.64.1,<5.0.0)
